AUTHORS
CHANGELOG
LICENSE
MANIFEST.in
README.rst
setup.py
tests/__init__.py
tests/conftest.py
tests/testapp/__init__.py
tests/testapp/settings.py
tests/testapp/migrations/__init__.py
tests/unit/__init__.py
tests/unit/test_jsonschema_generator.py
tests/unit/test_jsonschema_parser.py
wagtail_jsonschema_forms/__init__.py
wagtail_jsonschema_forms/jsonschema_generator.py
wagtail_jsonschema_forms/jsonschema_parser.py
wagtail_jsonschema_forms/mixins.py
wagtail_jsonschema_forms/models.py
wagtail_jsonschema_forms.egg-info/PKG-INFO
wagtail_jsonschema_forms.egg-info/SOURCES.txt
wagtail_jsonschema_forms.egg-info/dependency_links.txt
wagtail_jsonschema_forms.egg-info/requires.txt
wagtail_jsonschema_forms.egg-info/top_level.txt
wagtail_jsonschema_forms/__pycache__/__init__.cpython-35.pyc
wagtail_jsonschema_forms/__pycache__/jsonschema_generator.cpython-35.pyc
wagtail_jsonschema_forms/__pycache__/jsonschema_parser.cpython-35.pyc
wagtail_jsonschema_forms/__pycache__/mixins.cpython-35.pyc
wagtail_jsonschema_forms/__pycache__/models.cpython-35.pyc