Metadata-Version: 1.1
Name: wagtail-jsonschema-forms
Version: 0.1
Summary: Generate JsonSchema Forms from Wagtail's forms and validate it
Home-page: https://github.com/APSL/wagtail-jsonschema-forms
Author: Carlos Salom
Author-email: csalom@apsl.net
License: MIT
Platform: UNKNOWN
Classifier: Environment :: Web Environment
Classifier: Framework :: Django
Classifier: Intended Audience :: Developers
Classifier: Programming Language :: Python
Classifier: Programming Language :: Python :: 2
Classifier: Programming Language :: Python :: 2.7
Classifier: Programming Language :: Python :: 3
Classifier: Programming Language :: Python :: 3.4
Classifier: Programming Language :: Python :: 3.5
Classifier: Programming Language :: Python :: 3.6
Classifier: Operating System :: OS Independent
Classifier: Topic :: Software Development
